polarscore-0.5.0.dist-info/METADATA
polarscore-0.5.0.dist-info/WHEEL
polarscore-0.5.0.dist-info/licenses/LICENSE
polarscore/feature_selection.py
polarscore/woe.py
polarscore/bin.py
polarscore/__init__.py
polarscore/base.py
polarscore/_internal.abi3.so
polarscore-0.5.0.dist-info/RECORD
