Metadata-Version: 2.3
Name: polarscore
Version: 0.5.0
Requires-Dist: altair >=5.4.1
Requires-Dist: polars >=1.6.0
Requires-Dist: polarscore
Requires-Dist: scikit-learn >=1.5.1
License-File: LICENSE
Summary: Lightning-fast credit scorecard building with Polars
Author-email: Mark Wang <wxgter@gmail.com>
Requires-Python: >=3.9
